sbm/__init__.py
sbm/__main__.py
sbm/cli.py
sbm/config.py
sbm/core/__init__.py
sbm/core/diagnostics.py
sbm/core/full_workflow.py
sbm/core/git_operations.py
sbm/core/migration.py
sbm/core/site_initializer.py
sbm/core/validation.py
sbm/core/workflow.py
sbm/oem/__init__.py
sbm/oem/base.py
sbm/oem/default.py
sbm/oem/factory.py
sbm/oem/handler.py
sbm/oem/stellantis.py
sbm/scss/__init__.py
sbm/scss/parser.py
sbm/scss/processor.py
sbm/scss/transformer.py
sbm/scss/validator.py
sbm/utils/__init__.py
sbm/utils/errors.py
sbm/utils/logger.py
sbm_v2-2.5.0.dist-info/licenses/LICENSE
sbm_v2-2.5.0.dist-info/METADATA
sbm_v2-2.5.0.dist-info/WHEEL
sbm_v2-2.5.0.dist-info/entry_points.txt
sbm_v2-2.5.0.dist-info/top_level.txt
sbm_v2-2.5.0.dist-info/RECORD
