Metadata-Version: 2.4
Name: sbm-v2
Version: 2.5.0
Summary: Site Builder Migration Tool V2 - Team-friendly migration tool for DealerInspire dealer websites
Author: DealerInspire Development Team
License: MIT
Project-URL: Homepage, https://github.com/nate-hart-di/auto-sbm
Project-URL: Repository, https://github.com/nate-hart-di/auto-sbm
Project-URL: Documentation, https://github.com/nate-hart-di/auto-sbm/docs
Project-URL: Bug Tracker, https://github.com/nate-hart-di/auto-sbm/issues
Keywords: dealerinspire,migration,scss,site-builder
Classifier: Development Status :: 4 - Beta
Classifier: Intended Audience :: Developers
Classifier: License :: OSI Approved :: MIT License
Classifier: Programming Language :: Python :: 3
Classifier: Programming Language :: Python :: 3.8
Classifier: Programming Language :: Python :: 3.9
Classifier: Programming Language :: Python :: 3.10
Classifier: Programming Language :: Python :: 3.11
Requires-Python: >=3.8
License-File: LICENSE
Requires-Dist: click>=8.0.0
Requires-Dist: rich>=13.0.0
Requires-Dist: gitpython>=3.1.0
Requires-Dist: pyyaml>=6.0
Requires-Dist: requests>=2.28.0
Requires-Dist: mcp>=0.1.0
Requires-Dist: pathlib2>=2.3.0
Requires-Dist: colorama>=0.4.0
Requires-Dist: jinja2>=3.0.0
Requires-Dist: python-dotenv>=1.0.0
Provides-Extra: dev
Requires-Dist: pytest>=7.0.0; extra == "dev"
Requires-Dist: pytest-cov>=4.0.0; extra == "dev"
Requires-Dist: black>=22.0.0; extra == "dev"
Requires-Dist: flake8>=5.0.0; extra == "dev"
Requires-Dist: mypy>=1.0.0; extra == "dev"
Requires-Dist: pre-commit>=2.20.0; extra == "dev"
Dynamic: license-file
